MANIFEST.in
README.rst
setup.py
RubyFormatter/__init__.py
RubyFormatter/__main__.py
RubyFormatter/analizer.py
RubyFormatter/cmdParser.py
RubyFormatter/fileFormatter.py
RubyFormatter/formatter.py
RubyFormatter/log.py
RubyFormatter/rubyCodeParser.py
RubyFormatter/rubyFolderVerify.py
cmdline_ruby_formatter.egg-info/PKG-INFO
cmdline_ruby_formatter.egg-info/SOURCES.txt
cmdline_ruby_formatter.egg-info/dependency_links.txt
cmdline_ruby_formatter.egg-info/entry_points.txt
cmdline_ruby_formatter.egg-info/top_level.txt