Metadata-Version: 1.0
Name: cmdline-ruby-formatter
Version: 0.3.2
Summary: Python command line application bare bones template.
Home-page: UNKNOWN
Author: Lipsky Danial
Author-email: lipsky787@gmail.com
License: UNKNOWN
Platform: UNKNOWN
